{"entries": [{"id": "758c0ea4", "player": "Tristan da Silva", "stat": "PTS", "line": 8.5, "side": "OVER", "confidence_score": 87, "confidence_tier": "Elite", "model_prob": 0.55, "odds": 1.91, "result": "hit", "actual_value": 12.0, "logged_at": "2026-04-09T06:32:08.498242Z", "resolved_at": "2026-04-09T06:38:00.870595Z", "event_date": "", "source": "", "market_side": "", "market_disagrees": false, "notes": ""}, {"id": "59050307", "player": "Nickeil Alexander-Walker", "stat": "PRA", "line": 27.5, "side": "OVER", "confidence_score": 87, "confidence_tier": "Elite", "model_prob": 0.55, "odds": 1.73, "result": "hit", "actual_value": 31.0, "logged_at": "2026-04-10T02:59:36.664005Z", "resolved_at": "2026-04-10T02:59:43.043566Z", "event_date": "", "source": "manual", "market_side": "", "market_disagrees": false, "notes": ""}, {"id": "960551e2", "player": "Toumani Camara", "stat": "PTS", "line": 14.5, "side": "OVER", "confidence_score": 87, "confidence_tier": "Elite", "model_prob": 0.55, "odds": 1.79, "result": "hit", "actual_value": 18.0, "logged_at": "2026-04-10T03:00:17.543706Z", "resolved_at": "2026-04-10T03:00:22.266661Z", "event_date": "", "source": "manual", "market_side": "", "market_disagrees": false, "notes": ""}, {"id": "1c7e9e43", "player": "Sandro Mamukelashvili", "stat": "PR", "line": 14.5, "side": "OVER", "confidence_score": 87, "confidence_tier": "Elite", "model_prob": 0.55, "odds": 1.833, "result": "miss", "actual_value": 9.0, "logged_at": "2026-04-10T03:01:37.268818Z", "resolved_at": "2026-04-10T03:01:40.020580Z", "event_date": "", "source": "manual", "market_side": "", "market_disagrees": false, "notes": ""}, {"id": "5d0ff0ac", "player": "Luke Kennard", "stat": "PRA", "line": 23.5, "side": "OVER", "confidence_score": 64, "confidence_tier": "Medium", "model_prob": 0.55, "odds": 1.909, "result": "hit", "actual_value": 24.0, "logged_at": "2026-04-10T03:02:21.453337Z", "resolved_at": "2026-04-10T04:16:40.472270Z", "event_date": "", "source": "manual", "market_side": "", "market_disagrees": false, "notes": ""}, {"id": "2fa28ff3", "player": "VJ Edgecombe", "stat": "PR", "line": 23.5, "side": "OVER", "confidence_score": 87, "confidence_tier": "Elite", "model_prob": 0.55, "odds": 1.91, "result": "miss", "actual_value": 16.0, "logged_at": "2026-04-12T19:19:30.029465Z", "resolved_at": "2026-04-13T02:11:24.731418Z", "event_date": "", "source": "manual", "market_side": "", "market_disagrees": false, "notes": ""}, {"id": "2c6c64cb", "player": "Zaccharie Risacher", "stat": "PR", "line": 20.5, "side": "UNDER", "confidence_score": 76, "confidence_tier": "High", "model_prob": 0.55, "odds": 1.91, "result": "hit", "actual_value": 20.0, "logged_at": "2026-04-12T19:21:42.972035Z", "resolved_at": "2026-04-13T02:11:16.528971Z", "event_date": "", "source": "manual", "market_side": "", "market_disagrees": false, "notes": ""}, {"id": "f5e033a1", "player": "Toumani Camara", "stat": "PA", "line": 16.5, "side": "OVER", "confidence_score": 87, "confidence_tier": "Elite", "model_prob": 0.55, "odds": 1.91, "result": "hit", "actual_value": 17.0, "logged_at": "2026-04-12T19:22:43.656926Z", "resolved_at": "2026-04-13T02:49:54.506629Z", "event_date": "", "source": "manual", "market_side": "", "market_disagrees": false, "notes": ""}, {"id": "614837a2", "player": "Paolo Banchero", "stat": "PRA", "line": 33.5, "side": "OVER", "confidence_score": 64, "confidence_tier": "Medium", "model_prob": 0.55, "odds": 1.91, "result": "hit", "actual_value": 44.0, "logged_at": "2026-04-12T19:24:43.351196Z", "resolved_at": "2026-04-13T02:10:43.404622Z", "event_date": "", "source": "manual", "market_side": "", "market_disagrees": false, "notes": ""}, {"id": "44695b74", "player": "Darius Garland", "stat": "RA", "line": 10.5, "side": "UNDER", "confidence_score": 76, "confidence_tier": "High", "model_prob": 0.55, "odds": 1.91, "result": "hit", "actual_value": 7.0, "logged_at": "2026-04-12T19:26:31.277756Z", "resolved_at": "2026-04-13T03:01:23.711236Z", "event_date": "", "source": "manual", "market_side": "", "market_disagrees": false, "notes": ""}, {"id": "8e86263e", "player": "Jakob Poeltl", "stat": "PA", "line": 10.5, "side": "OVER", "confidence_score": 76, "confidence_tier": "High", "model_prob": 0.55, "odds": 1.91, "result": "hit", "actual_value": 13.0, "logged_at": "2026-04-12T19:28:21.855230Z", "resolved_at": "2026-04-13T02:11:05.474647Z", "event_date": "", "source": "manual", "market_side": "", "market_disagrees": false, "notes": ""}, {"id": "legacy-sqlite-1", "player": "Nikola Jokic", "stat": "REB", "line": 12.5, "side": "OVER", "confidence_score": 81, "confidence_tier": "strong", "model_prob": 0.62, "odds": 1.83, "result": "hit", "actual_value": 14.0, "logged_at": "2026-04-06T04:24:11.857001+00:00", "resolved_at": "2026-04-06T04:27:15.715840+00:00", "event_date": "2026-04-07", "source": "manual-test", "market_side": "OVER", "market_disagrees": false, "notes": ""}, {"id": "legacy-sqlite-2", "player": "Jalen Johnson", "stat": "3PM", "line": 1.5, "side": "OVER", "confidence_score": 77, "confidence_tier": "High", "model_prob": 0.6013, "odds": 1.91, "result": "hit", "actual_value": 2.0, "logged_at": "2026-04-06T04:45:05.258174+00:00", "resolved_at": "2026-04-06T04:45:19.518177+00:00", "event_date": "2026-04-06T00:00:00", "source": "analyzer", "market_side": "OVER", "market_disagrees": false, "notes": ""}, {"id": "e46cf762", "player": "Toumani Camara", "stat": "PRA", "line": 20.5, "side": "OVER", "confidence_score": 76, "confidence_tier": "High", "model_prob": 0.55, "odds": 1.91, "result": "miss", "actual_value": 12.0, "logged_at": "2026-04-14T20:18:27.690229Z", "resolved_at": "2026-04-15T04:49:13.008178Z", "event_date": "", "source": "manual", "market_side": "", "market_disagrees": false, "notes": ""}, {"id": "af507906", "player": "Devin Booker", "stat": "3PM", "line": 1.5, "side": "OVER", "confidence_score": 76, "confidence_tier": "High", "model_prob": 0.55, "odds": 1.91, "result": "miss", "actual_value": 0.0, "logged_at": "2026-04-15T03:54:47.251583Z", "resolved_at": "2026-04-15T04:49:08.850789Z", "event_date": "", "source": "manual", "market_side": "", "market_disagrees": false, "notes": ""}, {"id": "7e5d8cb5", "player": "Pelle Larsson", "stat": "PTS", "line": 9.5, "side": "OVER", "confidence_score": 76, "confidence_tier": "High", "model_prob": 0.55, "odds": 1.91, "result": "miss", "actual_value": 6.0, "logged_at": "2026-04-14T20:18:48.305232Z", "resolved_at": "2026-04-15T03:54:19.401146Z", "event_date": "", "source": "manual", "market_side": "", "market_disagrees": false, "notes": ""}, {"id": "0438a6d8", "player": "Jaime Jaquez Jr.", "stat": "PA", "line": 15.5, "side": "OVER", "confidence_score": 87, "confidence_tier": "Elite", "model_prob": 0.55, "odds": 1.91, "result": "hit", "actual_value": 21.0, "logged_at": "2026-04-15T03:54:01.825656Z", "resolved_at": "2026-04-15T03:54:08.971103Z", "event_date": "", "source": "manual", "market_side": "", "market_disagrees": false, "notes": ""}], "version": 1, "saved_at": 1776230404.7680097}